README.txt
setup.py
src/zif/__init__.py
src/zif.xtemplate.egg-info/PKG-INFO
src/zif.xtemplate.egg-info/SOURCES.txt
src/zif.xtemplate.egg-info/dependency_links.txt
src/zif.xtemplate.egg-info/namespace_packages.txt
src/zif.xtemplate.egg-info/not-zip-safe
src/zif.xtemplate.egg-info/requires.txt
src/zif.xtemplate.egg-info/top_level.txt
src/zif/xtemplate/README.txt
src/zif/xtemplate/__init__.py
src/zif/xtemplate/basetemplate.html
src/zif/xtemplate/ftests.py
src/zif/xtemplate/interfaces.py
src/zif/xtemplate/lxmlhtmlutils.py
src/zif/xtemplate/sanitizer.py
src/zif/xtemplate/sanitizer_README.txt
src/zif/xtemplate/tests.py
src/zif/xtemplate/xtemplate.py
src/zif/xtemplate/dtds/LICENSE.txt
src/zif/xtemplate/dtds/xhtml-lat1.ent
src/zif/xtemplate/dtds/xhtml-special.ent
src/zif/xtemplate/dtds/xhtml-symbol.ent
src/zif/xtemplate/dtds/xhtml1-frameset.dtd
src/zif/xtemplate/dtds/xhtml1-strict.dtd
src/zif/xtemplate/dtds/xhtml1-transitional.dtd
