Metadata-Version: 1.0
Name: zif.xtemplate
Version: 0.2.2
Summary: XML templating for Zope 3.
Home-page: http://zif.svn.sourceforge.net/viewvc/zif/zif.xtemplate
Author: Jim Washington
Author-email: jwashin@users.sourceforge.net
License: BSD
Keywords: xtemplate xml template zope3
Platform: UNKNOWN
